{"H00IvFdK34U+A4IYb+BzNA==":"header-2000x1330.jpg","L2UKuK7xDP1f09lp6HeQXg==":"header_2c-1400x938.jpg","BHDcjIOjX1mOykRYKvVDMA==":"header_2b-2000x1330.jpg","AQRQrpczPGT+hTd2JK2WHg==":"header_2c-2000x1340.jpg","ifCOe+E6VfEWuVExkTk/Hw==":"ag00038_-2000x1149.jpg","aWv7clTfC4Xni40cIc0f+Q==":"handyman_midsize-2000x1331.jpg","hfyULzFX9/PRPES/alo2ew==":"logo_shapeimage-2000x451.png","J9CejSnUMrCf5lLCOgt5og==":"logo_shapeimage_1_x380-2000x452.png","EwMvJiqlP1l9M2ZbiVoWog==":"homes_shapeimage-2000x922.png","qX1FHJgVr91RRKgVhflO2Q==":"homes_shapeimage_11_x380-2000x921.png","3z5WfW8W0EAybHoOoppPQQ==":"bird_transparent.gif","URXtFQUO/QkPu9h4g6s5Dw==":"handyman-logo-small-116x128.jpg","ReYDkowXRQkuQlyUUQc3AA==":"a-electrician.gif","bWuEcI4iczof4Y14SVJsQw==":"good_people_shapeimage-2000x496.png","wQUZpw750zzPo8hUWg57FA==":"good_people_shapeimage_1_x400-517x128.png","CBpi8zm9aqodaN+yUGOTOQ==":"abc_logo705x105_header_r072.gif","3OjKEfSvGWkm4gsop1Y2rg==":"abc_cleaning_x500-2000x1116.jpg"}